resource_container/ResourceContainer.py
resource_container/__init__.py
resource_container/factory.py
resource_container-1.1.dist-info/DESCRIPTION.rst
resource_container-1.1.dist-info/METADATA
resource_container-1.1.dist-info/RECORD
resource_container-1.1.dist-info/WHEEL
resource_container-1.1.dist-info/metadata.json
resource_container-1.1.dist-info/top_level.txt
tests/__init__.py
tests/container_test.py
