Metadata-Version: 2.0
Name: resource-container
Version: 1.1
Summary: A utility for managing Door43 Resource Containers
Home-page: https://github.com/unfoldingWord-dev/python-resource-container
Author: unfoldingWord
Author-email: joel@neutrinographics.com
License: MIT
Keywords: rc,resource container,client
Platform: UNKNOWN
Classifier: License :: OSI Approved :: MIT License
Classifier: Programming Language :: Python :: 2.7
Classifier: Programming Language :: Python :: 3
Classifier: Programming Language :: Python :: 3.3
Classifier: Programming Language :: Python :: 3.4
Classifier: Programming Language :: Python :: 3.5
Requires-Dist: pyyaml
Requires-Dist: uw-tools
